symbolism/__init__.py
symbolism/symbolism.py
symbolism-0.4.0.dist-info/LICENSE
symbolism-0.4.0.dist-info/METADATA
symbolism-0.4.0.dist-info/WHEEL
symbolism-0.4.0.dist-info/top_level.txt
symbolism-0.4.0.dist-info/RECORD
